nbcheckmate/__init__.py
nbcheckmate/nbcheckmate.py
nbcheckmate-0.1.6.dist-info/METADATA
nbcheckmate-0.1.6.dist-info/WHEEL
nbcheckmate-0.1.6.dist-info/top_level.txt
nbcheckmate-0.1.6.dist-info/RECORD
