Metadata-Version: 2.4
Name: nbcheckmate
Version: 0.1.6
Summary: Small package to test code inside a jupyter notebook
Author-email: Paul Chupot <paul.chupot@gmail.com>, Aloys Bernard <aloys.bernard@gmail.com>
Keywords: jupyter,notebook,testing,pytest
Requires-Python: >=3.10
Requires-Dist: dill>=0.3.9
Requires-Dist: pytest>=7.1.3
